nanowallet/__init__.py
nanowallet/errors.py
nanowallet/models.py
nanowallet/libs/__init__.py
nanowallet/libs/account_helper.py
nanowallet/libs/block.py
nanowallet/libs/rpc.py
nanowallet/utils/__init__.py
nanowallet/utils/amount_operations.py
nanowallet/utils/conversion.py
nanowallet/utils/decorators.py
nanowallet/utils/state_utils.py
nanowallet/utils/validation.py
nanowallet/wallets/__init__.py
nanowallet/wallets/authenticated_impl.py
nanowallet/wallets/protocols.py
nanowallet/wallets/read_only_impl.py
nanowallet/wallets/wallet_factory.py
nanowallet/wallets/components/__init__.py
nanowallet/wallets/components/block_operations.py
nanowallet/wallets/components/block_preparation.py
nanowallet/wallets/components/block_submission.py
nanowallet/wallets/components/query_operations.py
nanowallet/wallets/components/rpc_component.py
nanowallet/wallets/components/state_manager.py
nanowallet-0.1.8.dist-info/METADATA
nanowallet-0.1.8.dist-info/WHEEL
nanowallet-0.1.8.dist-info/top_level.txt
nanowallet-0.1.8.dist-info/RECORD
