Metadata-Version: 2.4
Name: nanowallet
Version: 0.1.8
Summary: async nano library for easy account management
Author: gr0vity
Project-URL: Homepage, https://github.com/gr0vity-dev/nanowallet_py
Requires-Python: >=3.7
Requires-Dist: nano_lib_py==0.5.1
Requires-Dist: nanorpc>=0.28.0
